{
  "disableRelatedObjectTab": {
    "inputs": [],
    "logic": [
      {
        "action": "setvar",
        "id": "046a1c56-0119-4c82-96f2-9d20fb693ea2",
        "isCommented": false,
        "type": "calculated",
        "value": {
          "function": "createNewStringArray",
          "library": "CirrusLibArray",
          "params": {},
          "returnType": "text array"
        },
        "variable": {
          "datatype": "text array",
          "name": "hideRelatedObjectsTab",
          "scope": "local"
        }
      },
      {
        "action": "setvar",
        "id": "88200905-fb34-4b40-8fa8-44d381a53add",
        "isCommented": false,
        "type": "calculated",
        "value": {
          "function": "getAppConfigProperty",
          "library": "CirrusLibConfigProperties",
          "params": {
            "propertyName": {
              "datatype": "text",
              "scope": "fixed",
              "value": "Solution.rpmEnabled"
            }
          },
          "returnType": "\u003cOutgoing\u003e"
        },
        "variable": {
          "datatype": "\u003cOutgoing\u003e",
          "name": "rpmEnabled",
          "scope": "local"
        }
      },
      {
        "action": "ifelse",
        "id": "f4c9844c-08c1-43ff-8cf3-d29f0962e414",
        "includeElse": true,
        "isCommented": false,
        "test": {
          "datatype": "\u003cOutgoing\u003e",
          "name": "rpmEnabled",
          "scope": "local"
        }
      },
      {
        "action": "ifelse",
        "id": "73365251-09e7-479d-95e2-bb7331821e96",
        "includeElse": true,
        "iselse": true,
        "main": "f4c9844c-08c1-43ff-8cf3-d29f0962e414",
        "test": {
          "datatype": "\u003cOutgoing\u003e",
          "name": "rpmEnabled",
          "scope": "local"
        }
      },
      {
        "action": "execfunc",
        "function": "push",
        "id": "44fda420-b5bf-48f2-83d0-11ba6b0f3cf9",
        "isCommented": false,
        "library": "CirrusLibArray",
        "params": {
          "array": {
            "datatype": "text array",
            "name": "hideRelatedObjectsTab",
            "scope": "local"
          },
          "value": {
            "datatype": "text",
            "scope": "fixed",
            "value": "relatedObjects"
          }
        },
        "returnType": "numeric"
      },
      {
        "action": "setprop",
        "function": "setHiddenTabsById",
        "id": "067f9da9-8a5b-466f-8df7-e762f81bf67f",
        "isCommented": false,
        "params": {
          "hiddenTabIds": {
            "datatype": "text array",
            "name": "hideRelatedObjectsTab",
            "scope": "local"
          }
        },
        "scope": "currentPage",
        "widgetId": "model_tabs"
      },
      {
        "action": "ifelse",
        "end": true,
        "id": "1e639545-df35-4ac8-99cf-a59f42a8a032",
        "includeElse": true,
        "isCommented": false,
        "main": "f4c9844c-08c1-43ff-8cf3-d29f0962e414",
        "test": {
          "datatype": "\u003cOutgoing\u003e",
          "name": "rpmEnabled",
          "scope": "local"
        }
      }
    ],
    "resolveEachStep": false,
    "sasProvided": true
  },
  "getCopySuffix": {
    "inputs": [
      {
        "datatype": "text",
        "name": "input_key"
      }
    ],
    "logic": [
      {
        "action": "addComment",
        "commentStep": "// Extract target objectId for filter condition",
        "id": "18b70e2c-e24c-4503-b323-c8c437e13eeb",
        "isCommented": false
      },
      {
        "action": "setvar",
        "id": "d488ddec-fc34-41b6-930e-0c4c700b8311",
        "isCommented": false,
        "type": "calculated",
        "value": {
          "function": "getCurrentObjectType",
          "library": "CirrusLibPageData",
          "params": {},
          "returnType": "text"
        },
        "variable": {
          "datatype": "text",
          "name": "objectType",
          "scope": "local"
        }
      },
      {
        "action": "setvar",
        "id": "5502d84b-2c16-4505-9539-520d78ff3ad0",
        "isCommented": false,
        "type": "calculated",
        "value": {
          "function": "replace",
          "library": "CirrusLibString",
          "params": {
            "mainString": {
              "datatype": "text",
              "scope": "fixed",
              "value": "contains(createdFrom,'__name_of_target__')"
            },
            "replacement": {
              "datatype": "text",
              "name": "input_key",
              "scope": "local"
            },
            "target": {
              "datatype": "text",
              "scope": "fixed",
              "value": "__name_of_target__"
            }
          },
          "returnType": "text"
        },
        "variable": {
          "datatype": "text",
          "name": "condition",
          "scope": "local"
        }
      },
      {
        "action": "addComment",
        "commentStep": "// Filter objects based on object type and condition",
        "id": "4ddd12d9-71b9-4e23-a2b1-a1bcefa9e256",
        "isCommented": false
      },
      {
        "action": "setvar",
        "id": "ef87cea6-ee70-447c-ab70-1a4a9d6f3797",
        "isCommented": false,
        "type": "calculated",
        "value": {
          "function": "fetchObjects",
          "library": "CirrusLibCirrusObject",
          "params": {
            "filter": {
              "datatype": "text",
              "name": "condition",
              "scope": "local"
            },
            "type": {
              "datatype": "text",
              "name": "objectType",
              "scope": "local"
            }
          },
          "returnType": "All Data"
        },
        "variable": {
          "datatype": "All Data",
          "name": "filteredObjects",
          "scope": "local"
        }
      },
      {
        "action": "setvar",
        "id": "ca83938f-1f68-4351-8dae-baec2cc2551b",
        "isCommented": false,
        "type": "calculated",
        "value": {
          "function": "jsonStringify",
          "library": "CirrusLibGeneral",
          "params": {
            "data": {
              "datatype": "All Data",
              "name": "filteredObjects",
              "scope": "local"
            }
          },
          "returnType": "\u003cIncoming\u003e"
        },
        "variable": {
          "datatype": "\u003cIncoming\u003e",
          "name": "objToString",
          "scope": "local"
        }
      },
      {
        "action": "setvar",
        "id": "87607c90-97ce-473c-afcd-4f2ed36cef01",
        "isCommented": false,
        "type": "calculated",
        "value": {
          "function": "convertStringToArray",
          "library": "CirrusLibArray",
          "params": {
            "string": {
              "name": "objToString",
              "scope": "local"
            }
          },
          "returnType": "\u003cOutgoing\u003e array"
        },
        "variable": {
          "datatype": "\u003cOutgoing\u003e array",
          "name": "stringToArr",
          "scope": "local"
        }
      },
      {
        "action": "addComment",
        "commentStep": "// count the number of instances and create copySuffix",
        "id": "24ff8c01-2c62-4c27-991d-12b4d920d47d",
        "isCommented": false
      },
      {
        "action": "setvar",
        "id": "fba07fb6-4c54-4449-af4d-5f8538f26f95",
        "isCommented": false,
        "type": "calculated",
        "value": {
          "datatype": "numeric",
          "function": "size",
          "library": "CirrusLibArray",
          "params": {
            "array": {
              "name": "stringToArr",
              "scope": "local"
            }
          },
          "returnType": "numeric"
        },
        "variable": {
          "datatype": "numeric",
          "name": "arrayLength",
          "scope": "local"
        }
      },
      {
        "action": "setvar",
        "id": "be349d48-7db6-491d-b3c3-a3876ebe062e",
        "isCommented": false,
        "type": "calculated",
        "value": {
          "datatype": "numeric",
          "function": "add",
          "library": "CirrusLibMath",
          "params": {
            "from": {
              "datatype": "numeric",
              "name": "arrayLength",
              "scope": "local"
            },
            "number": {
              "datatype": "numeric",
              "scope": "fixed",
              "value": 1
            }
          },
          "returnType": "numeric"
        },
        "variable": {
          "datatype": "numeric",
          "name": "arrayLength",
          "scope": "local"
        }
      },
      {
        "action": "setvar",
        "id": "d94e0b2f-de33-4109-96e5-80a1756637d4",
        "isCommented": false,
        "type": "calculated",
        "value": {
          "datatype": "text",
          "function": "toString",
          "library": "CirrusLibString",
          "params": {
            "value": {
              "datatype": "numeric",
              "name": "arrayLength",
              "scope": "local"
            }
          },
          "returnType": "text"
        },
        "variable": {
          "datatype": "text",
          "name": "copySuffix",
          "scope": "local"
        }
      },
      {
        "action": "setvar",
        "id": "bed4859a-044c-40f9-be45-953a245a3395",
        "isCommented": false,
        "type": "calculated",
        "value": {
          "datatype": "text",
          "function": "concat",
          "library": "CirrusLibString",
          "params": {
            "string1": {
              "datatype": "text",
              "scope": "fixed",
              "value": "_"
            },
            "string2": {
              "datatype": "text",
              "name": "copySuffix",
              "scope": "local"
            }
          },
          "returnType": "text"
        },
        "variable": {
          "datatype": "text",
          "name": "copySuffix",
          "scope": "local"
        }
      },
      {
        "action": "returnvar",
        "id": "306f42d2-ddf4-402b-beb6-e79e8f93c4bc",
        "isCommented": false,
        "variable": {
          "datatype": "text",
          "name": "copySuffix",
          "scope": "local"
        }
      }
    ],
    "resolveEachStep": false,
    "sasProvided": true
  },
  "getEditLinkForObjectInstance": {
    "inputs": [
      {
        "datatype": "text",
        "name": "input_objectType"
      },
      {
        "datatype": "text",
        "name": "input_key"
      }
    ],
    "logic": [
      {
        "action": "setvar",
        "id": "1eb7bf20-fc50-4c60-82e1-554e10a81196",
        "isCommented": false,
        "type": "calculated",
        "value": {
          "function": "getEditLocation",
          "library": "CirrusLibNav",
          "params": {
            "key": {
              "datatype": "text",
              "name": "input_key",
              "scope": "local"
            },
            "objectType": {
              "datatype": "text",
              "name": "input_objectType",
              "scope": "local"
            }
          },
          "returnType": "text"
        },
        "variable": {
          "datatype": "text",
          "name": "navLink",
          "scope": "local"
        }
      },
      {
        "action": "returnvar",
        "id": "608f2a63-5801-4504-b637-d5877dd657a8",
        "isCommented": false,
        "variable": {
          "datatype": "text",
          "name": "navLink",
          "scope": "local"
        }
      }
    ],
    "sasProvided": true
  },
  "getLocalisedObjectType": {
    "inputs": [],
    "logic": [
      {
        "action": "setvar",
        "id": "de43ec0e-26de-4312-8098-ea41df98e0c5",
        "type": "calculated",
        "value": {
          "function": "getCurrentObjectType",
          "library": "CirrusLibPageData",
          "params": {},
          "returnType": "text"
        },
        "variable": {
          "datatype": "text",
          "name": "objectType",
          "scope": "local"
        }
      },
      {
        "action": "setvar",
        "id": "bf8ace1f-02aa-4ceb-8e1f-58f64a8c2ae6",
        "type": "fixed",
        "value": {
          "datatype": "text",
          "dataval": ".schema.name.singular.title"
        },
        "variable": {
          "datatype": "text",
          "name": "i18nSuffix",
          "scope": "local"
        }
      },
      {
        "action": "setvar",
        "id": "6f603c67-ffe5-447f-b902-bcb605c35f6a",
        "type": "calculated",
        "value": {
          "function": "concat",
          "library": "CirrusLibString",
          "params": {
            "string1": {
              "datatype": "text",
              "name": "objectType",
              "scope": "local"
            },
            "string2": {
              "datatype": "text",
              "name": "i18nSuffix",
              "scope": "local"
            }
          },
          "returnType": "text"
        },
        "variable": {
          "datatype": "text",
          "name": "objectTypePropString",
          "scope": "local"
        }
      },
      {
        "action": "setvar",
        "id": "48a1e567-15fc-4015-ba12-37f761eda315",
        "type": "calculated",
        "value": {
          "function": "getMessageProperty",
          "library": "CirrusLibLocalization",
          "params": {
            "messageKey": {
              "datatype": "text",
              "name": "objectTypePropString",
              "scope": "local"
            }
          },
          "returnType": "text"
        },
        "variable": {
          "datatype": "text",
          "name": "localisedObjectType",
          "scope": "local"
        }
      },
      {
        "action": "returnvar",
        "id": "bfdac453-ee5e-41a4-9054-0289c21f975f",
        "variable": {
          "datatype": "text",
          "name": "localisedObjectType",
          "scope": "local"
        }
      }
    ],
    "resolveEachStep": false,
    "sasProvided": true
  },
  "onAnyEvent": {
    "inputs": [],
    "logic": [
      {
        "action": "setvar",
        "id": "d4c1dfc4-632b-46ae-a135-67a166a25ad6",
        "type": "calculated",
        "value": {
          "function": "getDiffJSONPatch",
          "library": "CirrusLibPageData",
          "params": {},
          "returnType": "Patch array"
        },
        "variable": {
          "datatype": "Patch array",
          "name": "patch",
          "scope": "local"
        }
      },
      {
        "action": "setvar",
        "id": "d3c1f6c8-099e-4027-85c8-7fae6fa783a1",
        "type": "calculated",
        "value": {
          "function": "isObjectPageDirty",
          "library": "CirrusLibCirrusObject",
          "params": {
            "patch": {
              "datatype": "Patch array",
              "name": "patch",
              "scope": "local"
            }
          },
          "returnType": "boolean"
        },
        "variable": {
          "datatype": "boolean",
          "name": "isPageDirty",
          "scope": "local"
        }
      },
      {
        "action": "setvar",
        "id": "e6055f2e-50ad-4533-9434-54d42a84a4fc",
        "type": "calculated",
        "value": {
          "function": "not",
          "library": "CirrusLibBoolean",
          "params": {
            "bool": {
              "datatype": "boolean",
              "name": "isPageDirty",
              "scope": "local"
            }
          },
          "returnType": "boolean"
        },
        "variable": {
          "datatype": "boolean",
          "name": "isNotDirty",
          "scope": "local"
        }
      },
      {
        "action": "setprop",
        "function": "setReadOnly",
        "id": "44a76eb6-71b3-4e7b-84ce-d3481cb6c029",
        "params": {
          "readOnly": {
            "datatype": "boolean",
            "name": "isNotDirty",
            "scope": "local"
          }
        },
        "scope": "currentPage",
        "widgetId": "save"
      },
      {
        "action": "execfunc",
        "function": "setTabDirty",
        "id": "989f93d8-d3c0-4878-a5d8-50b3b0739494",
        "library": "CirrusLibPageData",
        "params": {
          "isDirty": {
            "datatype": "boolean",
            "name": "isPageDirty",
            "scope": "local"
          }
        }
      }
    ],
    "sasProvided": true
  },
  "onCopyLoad": {
    "inputs": [
      {
        "datatype": "text",
        "name": "input_key"
      }
    ],
    "logic": [
      {
        "action": "setvar",
        "id": "b742185b-4abb-47cb-954b-fdb385a27a2c",
        "type": "calculated",
        "value": {
          "function": "getLinkTypeKeyForId",
          "library": "CirrusLibCirrusObjectLinkInstance",
          "params": {
            "linkTypeId": {
              "datatype": "text",
              "scope": "fixed",
              "value": "model_monitoringPlan"
            }
          },
          "returnType": "text"
        },
        "variable": {
          "datatype": "text",
          "name": "monitoringPlanLinkId",
          "scope": "local"
        }
      },
      {
        "action": "setvar",
        "id": "2d917f7d-43db-4c79-a2a7-98806841f01a",
        "isCommented": false,
        "type": "calculated",
        "value": {
          "function": "getLinkTypeKeyForId",
          "library": "CirrusLibCirrusObjectLinkInstance",
          "params": {
            "linkTypeId": {
              "datatype": "text",
              "scope": "fixed",
              "value": "model_model"
            }
          },
          "returnType": "text"
        },
        "variable": {
          "datatype": "text",
          "name": "modelModelLinkTypeId",
          "scope": "local"
        }
      },
      {
        "action": "setvar",
        "id": "422faa4b-25c1-40ab-87ac-0f5ad0af7d5c",
        "isCommented": false,
        "type": "calculated",
        "value": {
          "function": "getLinkTypeKeyForId",
          "library": "CirrusLibCirrusObjectLinkInstance",
          "params": {
            "linkTypeId": {
              "datatype": "text",
              "scope": "fixed",
              "value": "allocationScheme_defaultModel"
            }
          },
          "returnType": "text"
        },
        "variable": {
          "datatype": "text",
          "name": "allocationSchemeDefaultModelLinkId",
          "scope": "local"
        }
      },
      {
        "action": "setvar",
        "id": "508a1f37-f274-44b5-a701-f094e121975d",
        "isCommented": false,
        "type": "calculated",
        "value": {
          "function": "getLinkTypeKeyForId",
          "library": "CirrusLibCirrusObjectLinkInstance",
          "params": {
            "linkTypeId": {
              "datatype": "text",
              "scope": "fixed",
              "value": "allocationScheme_model"
            }
          },
          "returnType": "text"
        },
        "variable": {
          "datatype": "text",
          "name": "allocationSchemeModelLinkId",
          "scope": "local"
        }
      },
      {
        "action": "setvar",
        "id": "e75bb9a0-02ba-45a1-ae11-8c0c5a96fab9",
        "isCommented": false,
        "type": "calculated",
        "value": {
          "function": "getLinkTypeKeyForId",
          "library": "CirrusLibCirrusObjectLinkInstance",
          "params": {
            "linkTypeId": {
              "datatype": "text",
              "scope": "fixed",
              "value": "form_model"
            }
          },
          "returnType": "text"
        },
        "variable": {
          "datatype": "text",
          "name": "formModelLinkId",
          "scope": "local"
        }
      },
      {
        "action": "setvar",
        "id": "e77f4a4e-77de-42a6-bcf4-df98932224e2",
        "isCommented": false,
        "type": "calculated",
        "value": {
          "function": "getLinkTypeKeyForId",
          "library": "CirrusLibCirrusObjectLinkInstance",
          "params": {
            "linkTypeId": {
              "datatype": "text",
              "scope": "fixed",
              "value": "wfTemplate_model"
            }
          },
          "returnType": "text"
        },
        "variable": {
          "datatype": "text",
          "name": "wfTemplateModelLinkId",
          "scope": "local"
        }
      },
      {
        "action": "setvar",
        "id": "b68e122e-7725-42fb-87f5-b22d3b082172",
        "isCommented": false,
        "type": "calculated",
        "value": {
          "function": "getLinkTypeKeyForId",
          "library": "CirrusLibCirrusObjectLinkInstance",
          "params": {
            "linkTypeId": {
              "datatype": "text",
              "scope": "fixed",
              "value": "analysisRun_param_models"
            }
          },
          "returnType": "text"
        },
        "variable": {
          "datatype": "text",
          "name": "analysisRunParamModelsLinkId",
          "scope": "local"
        }
      },
      {
        "action": "setvar",
        "id": "e183f164-2ea2-461d-a930-722583eab66f",
        "type": "calculated",
        "value": {
          "function": "createNewStringArray",
          "library": "CirrusLibArray",
          "params": {},
          "returnType": "text array"
        },
        "variable": {
          "datatype": "text array",
          "name": "linkTypeKeys",
          "scope": "local"
        }
      },
      {
        "action": "execfunc",
        "function": "insert",
        "id": "d528fba4-5bc2-4880-b7e3-7e97570152e4",
        "library": "CirrusLibArray",
        "params": {
          "array": {
            "datatype": "text array",
            "name": "linkTypeKeys",
            "scope": "local"
          },
          "value": {
            "datatype": "text",
            "name": "monitoringPlanLinkId",
            "scope": "local"
          }
        },
        "returnType": "numeric"
      },
      {
        "action": "execfunc",
        "function": "push",
        "id": "24d62cba-7b15-4dcb-90cc-b48585500f32",
        "isCommented": false,
        "library": "CirrusLibArray",
        "params": {
          "array": {
            "datatype": "text array",
            "name": "linkTypeKeys",
            "scope": "local"
          },
          "value": {
            "datatype": "text",
            "name": "allocationSchemeDefaultModelLinkId",
            "scope": "local"
          }
        },
        "returnType": "numeric"
      },
      {
        "action": "execfunc",
        "function": "push",
        "id": "f47a351c-489e-4aa2-94bb-fd8e697b8b53",
        "isCommented": false,
        "library": "CirrusLibArray",
        "params": {
          "array": {
            "datatype": "text array",
            "name": "linkTypeKeys",
            "scope": "local"
          },
          "value": {
            "datatype": "text",
            "name": "allocationSchemeModelLinkId",
            "scope": "local"
          }
        },
        "returnType": "numeric"
      },
      {
        "action": "execfunc",
        "function": "push",
        "id": "411a2f4a-ce64-4ecb-a475-b5a527ce7e9c",
        "isCommented": false,
        "library": "CirrusLibArray",
        "params": {
          "array": {
            "datatype": "text array",
            "name": "linkTypeKeys",
            "scope": "local"
          },
          "value": {
            "datatype": "text",
            "name": "formModelLinkId",
            "scope": "local"
          }
        },
        "returnType": "numeric"
      },
      {
        "action": "execfunc",
        "function": "push",
        "id": "15269a05-420d-4037-9b6b-833e229c38b1",
        "isCommented": false,
        "library": "CirrusLibArray",
        "params": {
          "array": {
            "datatype": "text array",
            "name": "linkTypeKeys",
            "scope": "local"
          },
          "value": {
            "datatype": "text",
            "name": "analysisRunParamModelsLinkId",
            "scope": "local"
          }
        },
        "returnType": "numeric"
      },
      {
        "action": "execfunc",
        "function": "push",
        "id": "880fd2f5-a306-468e-863b-ae0ec8303b73",
        "isCommented": false,
        "library": "CirrusLibArray",
        "params": {
          "array": {
            "datatype": "text array",
            "name": "linkTypeKeys",
            "scope": "local"
          },
          "value": {
            "datatype": "text",
            "name": "modelModelLinkTypeId",
            "scope": "local"
          }
        },
        "returnType": "numeric"
      },
      {
        "action": "execfunc",
        "function": "push",
        "id": "52f2d5d5-1312-4294-b41a-b5f4d919c417",
        "isCommented": false,
        "library": "CirrusLibArray",
        "params": {
          "array": {
            "datatype": "text array",
            "name": "linkTypeKeys",
            "scope": "local"
          },
          "value": {
            "datatype": "text",
            "name": "wfTemplateModelLinkId",
            "scope": "local"
          }
        },
        "returnType": "numeric"
      },
      {
        "action": "setvar",
        "id": "0f23f8e3-8ee6-46e0-9d3c-25dbf1b31997",
        "type": "calculated",
        "value": {
          "function": "split",
          "library": "CirrusLibString",
          "params": {
            "separator": {
              "datatype": "text",
              "scope": "fixed",
              "value": ","
            },
            "string": {
              "datatype": "text",
              "scope": "fixed",
              "value": "statusCd"
            }
          },
          "returnType": "text array"
        },
        "variable": {
          "datatype": "text array",
          "name": "fieldsToExclude",
          "scope": "local"
        }
      },
      {
        "action": "setvar",
        "id": "773f5ee2-eb94-4c2d-bc0b-9f1ad0bae767",
        "type": "calculated",
        "value": {
          "function": "getCopySuffix",
          "library": "$interactions$",
          "params": {
            "input_key": {
              "datatype": "text",
              "name": "input_key",
              "scope": "local"
            }
          }
        },
        "variable": {
          "datatype": "text",
          "name": "copySuffix",
          "scope": "local"
        }
      },
      {
        "action": "execfunc",
        "function": "loadObjectCopyAsDraft",
        "id": "a1b4f39f-fdc8-477e-a6bb-1e46567bd107",
        "library": "CirrusLibCirrusObject",
        "params": {
          "copyClassifications": {
            "datatype": "boolean",
            "scope": "fixed",
            "value": true
          },
          "copyCustomFields": {
            "datatype": "boolean",
            "scope": "fixed",
            "value": true
          },
          "copyObjectLinks": {
            "datatype": "boolean",
            "scope": "fixed",
            "value": true
          },
          "copySuffix": {
            "datatype": "text",
            "name": "copySuffix",
            "scope": "local"
          },
          "fieldsToExclude": {
            "datatype": "text array",
            "name": "fieldsToExclude",
            "scope": "local"
          },
          "linkFieldsToExclude": {
            "datatype": "text array",
            "name": "linkTypeKeys",
            "scope": "local"
          },
          "objectKey": {
            "datatype": "text",
            "name": "input_key",
            "scope": "local"
          }
        },
        "returnType": "All Data"
      },
      {
        "action": "execfunc",
        "function": "onDraftLoad",
        "id": "5761d6d5-cc90-447c-b928-8ebe5e49fa04",
        "library": "$interactions$",
        "params": {}
      }
    ],
    "sasProvided": true
  },
  "onDraftLoad": {
    "inputs": [
      {
        "datatype": "numeric",
        "name": "input_id"
      }
    ],
    "logic": [
      {
        "action": "execfunc",
        "function": "showLoadingOverlay",
        "id": "da37cced-9648-4623-ba40-4017fdc9b003",
        "isCommented": false,
        "library": "CirrusLibPage",
        "params": {}
      },
      {
        "action": "setvar",
        "id": "3c2acbce-2558-482d-a7e1-9381a65d8939",
        "isCommented": false,
        "type": "calculated",
        "value": {
          "function": "getAllData",
          "library": "CirrusLibPageData",
          "params": {},
          "returnType": "All Data"
        },
        "variable": {
          "datatype": "All Data",
          "name": "pageData",
          "scope": "local"
        }
      },
      {
        "action": "setvar",
        "id": "077451f4-b320-4bf4-9533-02c201e149ac",
        "isCommented": false,
        "type": "calculated",
        "value": {
          "function": "get",
          "library": "CirrusLibObject",
          "params": {
            "name": {
              "datatype": "text",
              "scope": "fixed",
              "value": "createdFrom"
            },
            "object": {
              "datatype": "All Data",
              "name": "pageData",
              "scope": "local"
            }
          },
          "returnType": "\u003cany\u003e"
        },
        "variable": {
          "datatype": "\u003cany\u003e",
          "name": "createdFrom",
          "scope": "local"
        }
      },
      {
        "action": "setvar",
        "id": "e7bc9385-018f-4b55-b006-e003f2dc521e",
        "isCommented": false,
        "type": "calculated",
        "value": {
          "function": "isNullOrUndefined",
          "library": "CirrusLibGeneral",
          "params": {
            "value": {
              "name": "createdFrom",
              "scope": "local"
            }
          },
          "returnType": "boolean"
        },
        "variable": {
          "datatype": "boolean",
          "name": "isCreatedFromEmpty",
          "scope": "local"
        }
      },
      {
        "action": "ifelse",
        "id": "5c041a19-4a45-440f-b7b9-9a03eb5e4a87",
        "includeElse": true,
        "isCommented": false,
        "test": {
          "datatype": "boolean",
          "name": "isCreatedFromEmpty",
          "scope": "local"
        }
      },
      {
        "action": "execfunc",
        "function": "loadDraftObject",
        "id": "e5c12f08-3c9a-440a-9e6e-eb088be9c4b0",
        "library": "CirrusLibCirrusObject",
        "params": {},
        "returnType": "All Data"
      },
      {
        "action": "execfunc",
        "function": "setModelExecTypeDefault",
        "id": "cbefa98a-1327-44f2-bce8-17919cc69faf",
        "isCommented": false,
        "library": "$interactions$",
        "params": {}
      },
      {
        "action": "ifelse",
        "id": "33ee5272-31e0-4abb-b6e0-c198745c4525",
        "includeElse": true,
        "isCommented": false,
        "iselse": true,
        "main": "5c041a19-4a45-440f-b7b9-9a03eb5e4a87",
        "test": {
          "datatype": "boolean",
          "name": "isCreatedFromEmpty",
          "scope": "local"
        }
      },
      {
        "action": "setvar",
        "id": "26bd0d98-aaa9-495f-8a3d-d00197d3fdae",
        "isCommented": false,
        "type": "calculated",
        "value": {
          "function": "get",
          "library": "CirrusLibObject",
          "params": {
            "name": {
              "datatype": "text",
              "scope": "fixed",
              "value": "execTypeCd"
            },
            "object": {
              "datatype": "All Data",
              "name": "pageData",
              "scope": "local"
            }
          },
          "returnType": "\u003cany\u003e"
        },
        "variable": {
          "datatype": "\u003cany\u003e",
          "name": "execTypeCd",
          "objectType": "Model",
          "scope": "field",
          "set-field": "execTypeCd",
          "target": "$self$"
        }
      },
      {
        "action": "setvar",
        "id": "7779d853-a2c1-4757-b931-5f60f2f72b8f",
        "isCommented": false,
        "type": "calculated",
        "value": {
          "function": "get",
          "library": "CirrusLibObject",
          "params": {
            "name": {
              "datatype": "text",
              "scope": "fixed",
              "value": "engineCd"
            },
            "object": {
              "datatype": "All Data",
              "name": "pageData",
              "scope": "local"
            }
          },
          "returnType": "\u003cany\u003e"
        },
        "variable": {
          "datatype": "\u003cany\u003e",
          "name": "engineCd",
          "objectType": "Model",
          "scope": "field",
          "set-field": "engineCd",
          "target": "$self$"
        }
      },
      {
        "action": "setvar",
        "id": "8b0df3c1-a7b4-4d8b-ba12-bf626260c11b",
        "isCommented": false,
        "type": "fixed",
        "value": {
          "datatype": "text",
          "dataval": "TEST"
        },
        "variable": {
          "datatype": "text",
          "name": "statusCd",
          "objectType": "Model",
          "scope": "field",
          "set-field": "statusCd",
          "target": "$self$"
        }
      },
      {
        "action": "ifelse",
        "end": true,
        "id": "37649c96-fdbb-42a4-9e8e-0fc20e00f674",
        "includeElse": true,
        "isCommented": false,
        "main": "5c041a19-4a45-440f-b7b9-9a03eb5e4a87",
        "test": {
          "datatype": "boolean",
          "name": "isCreatedFromEmpty",
          "scope": "local"
        }
      },
      {
        "action": "execfunc",
        "function": "setRequiredFields",
        "id": "b2a4821a-0ba6-4068-a529-c1bd1efdd1df",
        "library": "$interactions$",
        "params": {}
      },
      {
        "action": "execfunc",
        "function": "disableRelatedObjectTab",
        "id": "a7b17953-2346-4b4f-b398-1c1115fdf8e1",
        "isCommented": false,
        "library": "$interactions$",
        "params": {}
      },
      {
        "action": "setvar",
        "id": "2bca7061-a38c-4e6b-a5c2-0f682c98af3f",
        "type": "calculated",
        "value": {
          "function": "getLocalisedObjectType",
          "library": "$interactions$",
          "params": {},
          "returnType": "text"
        },
        "variable": {
          "datatype": "text",
          "name": "objectType",
          "scope": "local"
        }
      },
      {
        "action": "setvar",
        "id": "b5742c67-ab43-45e4-a642-1adea308c059",
        "type": "calculated",
        "value": {
          "function": "concat",
          "library": "CirrusLibString",
          "params": {
            "string1": {
              "datatype": "text",
              "name": "objectType",
              "scope": "local"
            },
            "string2": {
              "datatype": "text",
              "scope": "fixed",
              "value": ": "
            }
          },
          "returnType": "text"
        },
        "variable": {
          "datatype": "text",
          "name": "name_str",
          "scope": "local"
        }
      },
      {
        "action": "setvar",
        "id": "abc939d1-45df-44b5-a739-898dec76a0a9",
        "type": "variable",
        "value": {
          "datatype": "text",
          "name": "name_str",
          "scope": "local"
        },
        "variable": {
          "datatype": "text",
          "name": "name_readonly",
          "scope": "data",
          "target": "$self$"
        }
      },
      {
        "action": "execfunc",
        "function": "setReadOnlyFields",
        "id": "728dd132-0254-45bb-8276-f739968d9e48",
        "library": "$interactions$",
        "params": {}
      },
      {
        "action": "setvar",
        "id": "3d32c8ff-73cb-4a7d-aa55-ee58c2984855",
        "isCommented": false,
        "type": "calculated",
        "value": {
          "function": "isRiskEngineAvailable",
          "library": "CirrusLibCirrusCoreRiskEngine",
          "params": {},
          "returnType": "boolean"
        },
        "variable": {
          "datatype": "boolean",
          "name": "isREAvailable",
          "scope": "local"
        }
      },
      {
        "action": "execfunc",
        "function": "setEngineDropdown",
        "id": "bf14744b-4fce-4815-b5f8-cabbf566e168",
        "isCommented": false,
        "library": "$interactions$",
        "params": {
          "input_isREAvailable": {
            "datatype": "boolean",
            "name": "isREAvailable",
            "scope": "local"
          }
        }
      },
      {
        "action": "setvar",
        "id": "3e086db1-c9f5-4051-8593-161b1d2d3dba",
        "isCommented": false,
        "type": "calculated",
        "value": {
          "function": "not",
          "library": "CirrusLibBoolean",
          "params": {
            "bool": {
              "datatype": "boolean",
              "name": "isCreatedFromEmpty",
              "scope": "local"
            }
          },
          "returnType": "boolean"
        },
        "variable": {
          "datatype": "boolean",
          "name": "createdFromNotEmpty",
          "scope": "local"
        }
      },
      {
        "action": "ifelse",
        "id": "efbc95b1-844d-4e49-bbac-514542006ea2",
        "isCommented": false,
        "test": {
          "datatype": "boolean",
          "name": "createdFromNotEmpty",
          "scope": "local"
        }
      },
      {
        "action": "execfunc",
        "function": "onExecTypeChange",
        "id": "e664451a-c3b4-47f8-8f36-38c07460fe1c",
        "isCommented": false,
        "library": "$interactions$",
        "params": {
          "input_value": {
            "datatype": "text",
            "name": "execTypeCd",
            "objectType": "Model",
            "scope": "field",
            "set-field": "execTypeCd",
            "target": "$self$"
          }
        }
      },
      {
        "action": "ifelse",
        "end": true,
        "id": "89773ee2-9db3-402e-a6f7-adf686d1dcf3",
        "isCommented": false,
        "main": "efbc95b1-844d-4e49-bbac-514542006ea2",
        "test": {
          "datatype": "boolean",
          "name": "createdFromNotEmpty",
          "scope": "local"
        }
      },
      {
        "action": "execfunc",
        "function": "hideLoadingOverlay",
        "id": "e0de814b-91ed-4c9b-9660-b3ba6a0a436d",
        "isCommented": false,
        "library": "CirrusLibPage",
        "params": {}
      }
    ],
    "sasProvided": true
  },
  "onEditLoad": {
    "inputs": [
      {
        "datatype": "text",
        "name": "input_key"
      }
    ],
    "logic": [
      {
        "action": "setvar",
        "id": "1de60fb6-a5d2-41f3-ba39-06c9f893c9fc",
        "type": "calculated",
        "value": {
          "function": "isObjectDeleted",
          "library": "CirrusLibCirrusObject",
          "params": {
            "objectKey": {
              "datatype": "text",
              "name": "input_key",
              "scope": "local"
            }
          },
          "returnType": "boolean"
        },
        "variable": {
          "datatype": "boolean",
          "name": "objectIsDeleted",
          "scope": "local"
        }
      },
      {
        "action": "ifelse",
        "id": "7aeff532-1dc5-4a34-8375-fea01f4b9d59",
        "test": {
          "datatype": "boolean",
          "name": "objectIsDeleted",
          "scope": "local"
        }
      },
      {
        "action": "returnvar",
        "id": "f41755f5-3e25-4573-bd74-7cccf765f069",
        "variable": {
          "datatype": "boolean",
          "name": "objectIsDeleted",
          "scope": "local"
        }
      },
      {
        "action": "ifelse",
        "end": true,
        "id": "3d734e7f-1d3d-450f-9741-8434ef42fa16",
        "main": "7aeff532-1dc5-4a34-8375-fea01f4b9d59",
        "test": {
          "datatype": "boolean",
          "name": "objectIsDeleted",
          "scope": "local"
        }
      },
      {
        "action": "execfunc",
        "function": "loadExistingObject",
        "id": "113780db-35cf-432a-b6b8-628827e9f424",
        "library": "CirrusLibCirrusObject",
        "params": {
          "key": {
            "datatype": "text",
            "name": "input_key",
            "scope": "local"
          }
        },
        "returnType": "All Data"
      },
      {
        "action": "execfunc",
        "function": "setRequiredFields",
        "id": "8d0ba74a-f6f2-45ee-aa15-91ac88ab5e26",
        "library": "$interactions$",
        "params": {}
      },
      {
        "action": "execfunc",
        "function": "setReadOnlyFields",
        "id": "5635048b-481b-4b58-a77f-a65d8debd5cc",
        "library": "$interactions$",
        "params": {}
      },
      {
        "action": "execfunc",
        "function": "disableRelatedObjectTab",
        "id": "4e156125-4e8f-4378-8478-6edc81811c42",
        "library": "$interactions$",
        "params": {}
      },
      {
        "action": "setvar",
        "id": "ea668192-7186-4956-b56b-44ed46857906",
        "type": "fixed",
        "value": {
          "datatype": "boolean",
          "dataval": true
        },
        "variable": {
          "datatype": "boolean",
          "name": "true",
          "scope": "local"
        }
      },
      {
        "action": "setprop",
        "function": "setReadOnly",
        "id": "3cd8b73c-e9c8-45a7-bbbc-a5e434ae2ebd",
        "params": {
          "readOnly": {
            "datatype": "boolean",
            "name": "true",
            "scope": "local"
          }
        },
        "widgetId": "objectId"
      },
      {
        "action": "execfunc",
        "function": "onNameChange",
        "id": "f84f9ce9-5301-4eb2-8582-e1fdfb12ea85",
        "library": "$interactions$",
        "params": {
          "input_value": {
            "datatype": "text",
            "name": "name",
            "scope": "field"
          }
        }
      },
      {
        "action": "setvar",
        "id": "1889ea8e-02f5-430c-a955-873dbe0626b7",
        "type": "variable",
        "value": {
          "datatype": "text",
          "name": "engineModelUri",
          "scope": "field"
        },
        "variable": {
          "datatype": "text",
          "name": "RiskEngineProjectSelector",
          "scope": "data"
        }
      },
      {
        "action": "setprop",
        "function": "setActiveLayoutName",
        "id": "a277e97e-0fe6-43f8-a9ea-69a94198505d",
        "params": {
          "activeTab": {
            "datatype": "text",
            "name": "engineCd",
            "scope": "field"
          }
        },
        "widgetId": "EngineWidgetContainer"
      },
      {
        "action": "setprop",
        "function": "setActiveLayoutName",
        "id": "41200338-4a9b-4b53-9c52-1c1a721fd2c6",
        "params": {
          "activeTab": {
            "datatype": "text",
            "name": "engineCd",
            "scope": "field"
          }
        },
        "widgetId": "CodeContainer"
      },
      {
        "action": "setvar",
        "id": "8e3fd5d8-898a-485f-a2bc-4a15f60413b3",
        "type": "calculated",
        "value": {
          "function": "isRiskEngineAvailable",
          "library": "CirrusLibCirrusCoreRiskEngine",
          "params": {},
          "returnType": "boolean"
        },
        "variable": {
          "datatype": "boolean",
          "name": "isREAvailable",
          "scope": "local"
        }
      },
      {
        "action": "execfunc",
        "function": "setEngineDropdown",
        "id": "1958596d-b0da-405e-baed-90565679aced",
        "library": "$interactions$",
        "params": {
          "input_isREAvailable": {
            "datatype": "boolean",
            "name": "isREAvailable",
            "scope": "local"
          }
        }
      },
      {
        "action": "execfunc",
        "function": "onExecTypeChange",
        "id": "1862c6e6-ac41-44ce-94fa-ceced3d35144",
        "library": "$interactions$",
        "params": {
          "input_value": {
            "datatype": "text",
            "name": "execTypeCd",
            "scope": "field"
          }
        }
      }
    ],
    "sasProvided": true
  },
  "onEngineChange": {
    "inputs": [
      {
        "datatype": "text",
        "name": "input_value"
      }
    ],
    "logic": [
      {
        "action": "setprop",
        "function": "setActiveLayoutName",
        "id": "16e77e2b-10d6-43f9-9b0f-a34f24eb4d19",
        "params": {
          "activeTab": {
            "datatype": "text",
            "name": "engineCd",
            "objectType": "Model",
            "scope": "field",
            "set-field": "engineCd",
            "target": "$self$"
          }
        },
        "scope": "currentPage",
        "widgetId": "EngineWidgetContainer"
      },
      {
        "action": "setvar",
        "id": "231836d8-5b3d-4620-889d-260d994307b5",
        "type": "fixed",
        "value": {
          "datatype": "text",
          "dataval": ""
        },
        "variable": {
          "datatype": "text",
          "name": "engineModelUri",
          "objectType": "Model",
          "scope": "field",
          "set-field": "engineModelUri",
          "target": "$self$"
        }
      },
      {
        "action": "setvar",
        "id": "941583ca-04ab-48cd-9e99-08ce50bbba1a",
        "type": "fixed",
        "value": {
          "datatype": "text",
          "dataval": ""
        },
        "variable": {
          "datatype": "text",
          "name": "RiskEngineProjectSelector",
          "scope": "data",
          "target": "$self$"
        }
      },
      {
        "action": "setprop",
        "function": "setActiveLayoutName",
        "id": "67e8c7dd-7178-4514-81fb-afbbce5cfca7",
        "isCommented": false,
        "params": {
          "activeTab": {
            "datatype": "text",
            "name": "input_value",
            "scope": "local"
          }
        },
        "scope": "currentPage",
        "widgetId": "CodeContainer"
      }
    ],
    "sasProvided": true
  },
  "onExecTypeChange": {
    "inputs": [
      {
        "datatype": "text",
        "name": "input_value"
      }
    ],
    "logic": [
      {
        "action": "setvar",
        "id": "e160f7c5-5d1a-49d2-9777-8d24023a5b9a",
        "type": "calculated",
        "value": {
          "function": "strEquals",
          "library": "CirrusLibString",
          "params": {
            "string1": {
              "datatype": "text",
              "name": "input_value",
              "scope": "local"
            },
            "string2": {
              "datatype": "text",
              "scope": "fixed",
              "value": "ALL"
            }
          },
          "returnType": "boolean"
        },
        "variable": {
          "datatype": "boolean",
          "name": "isExecTypeALL",
          "scope": "local"
        }
      },
      {
        "action": "ifelse",
        "id": "1ee96fab-b47f-4c2e-8941-c9006996ab20",
        "includeElse": true,
        "test": {
          "datatype": "boolean",
          "name": "isExecTypeALL",
          "scope": "local"
        }
      },
      {
        "action": "setvar",
        "id": "5286a4d7-4f41-4258-bd85-60c8a1c698c8",
        "type": "fixed",
        "value": {
          "datatype": "text",
          "dataval": "SAS"
        },
        "variable": {
          "datatype": "text",
          "name": "engineCd",
          "objectType": "Model",
          "scope": "field",
          "set-field": "engineCd",
          "target": "$self$"
        }
      },
      {
        "action": "setprop",
        "function": "setReadOnly",
        "id": "c8029efc-d3da-4df9-ac7d-90d58592df5a",
        "params": {
          "readOnly": {
            "datatype": "boolean",
            "scope": "fixed",
            "value": true
          }
        },
        "widgetId": "engineCd"
      },
      {
        "action": "setprop",
        "function": "setHidden",
        "id": "f9149669-fd38-4ead-a4b0-f2e526f64604",
        "params": {
          "hidden": {
            "datatype": "boolean",
            "scope": "fixed",
            "value": true
          }
        },
        "widgetId": "RiskEngineProjectSelector"
      },
      {
        "action": "setprop",
        "function": "setActiveLayoutName",
        "id": "f82dade4-067b-450d-8fd6-660322274ca3",
        "params": {
          "activeTab": {
            "datatype": "text",
            "name": "input_value",
            "scope": "local"
          }
        },
        "widgetId": "CodeContainer"
      },
      {
        "action": "ifelse",
        "id": "ce112483-38d9-4ae6-994f-51d1b92d8400",
        "includeElse": true,
        "iselse": true,
        "main": "1ee96fab-b47f-4c2e-8941-c9006996ab20",
        "test": {
          "datatype": "boolean",
          "name": "isExecTypeALL",
          "scope": "local"
        }
      },
      {
        "action": "setvar",
        "id": "ac57a38f-5fa2-4b42-a670-259e5f2de04b",
        "type": "calculated",
        "value": {
          "function": "strEquals",
          "library": "CirrusLibString",
          "params": {
            "string1": {
              "datatype": "text",
              "name": "input_value",
              "scope": "local"
            },
            "string2": {
              "datatype": "text",
              "scope": "fixed",
              "value": "BEPOVERLAY"
            }
          },
          "returnType": "boolean"
        },
        "variable": {
          "datatype": "boolean",
          "name": "isExecTypeBEPOVERLAY",
          "scope": "local"
        }
      },
      {
        "action": "ifelse",
        "id": "f12a4ee6-8dc5-401a-be44-45eff52a334a",
        "includeElse": true,
        "test": {
          "datatype": "boolean",
          "name": "isExecTypeBEPOVERLAY",
          "scope": "local"
        }
      },
      {
        "action": "setvar",
        "id": "5bfc2121-1892-4029-84f2-d40f3fa830b5",
        "type": "fixed",
        "value": {
          "datatype": "text",
          "dataval": "SAS"
        },
        "variable": {
          "datatype": "text",
          "name": "engineCd",
          "objectType": "Model",
          "scope": "field",
          "set-field": "engineCd",
          "target": "$self$"
        }
      },
      {
        "action": "setprop",
        "function": "setReadOnly",
        "id": "b303582d-1d2b-4776-9194-63b02c25ffc6",
        "params": {
          "readOnly": {
            "datatype": "boolean",
            "scope": "fixed",
            "value": true
          }
        },
        "widgetId": "engineCd"
      },
      {
        "action": "setprop",
        "function": "setHidden",
        "id": "86ecc2d8-b328-46b0-8fcd-afd8e613a1db",
        "params": {
          "hidden": {
            "datatype": "boolean",
            "scope": "fixed",
            "value": true
          }
        },
        "widgetId": "RiskEngineProjectSelector"
      },
      {
        "action": "setprop",
        "function": "setActiveLayoutName",
        "id": "ce4d6b14-5a89-4b23-9917-1fa4c18ac127",
        "params": {
          "activeTab": {
            "datatype": "text",
            "name": "engineCd",
            "objectType": "Model",
            "scope": "field",
            "set-field": "engineCd",
            "target": "$self$"
          }
        },
        "widgetId": "CodeContainer"
      },
      {
        "action": "ifelse",
        "id": "57789329-c5e3-4915-baff-537e1649f46c",
        "includeElse": true,
        "iselse": true,
        "main": "f12a4ee6-8dc5-401a-be44-45eff52a334a",
        "test": {
          "datatype": "boolean",
          "name": "isExecTypeBEPOVERLAY",
          "scope": "local"
        }
      },
      {
        "action": "setprop",
        "function": "setReadOnly",
        "id": "76ddf020-293d-456a-95b4-f5d66c8f592a",
        "params": {
          "readOnly": {
            "datatype": "boolean",
            "scope": "fixed",
            "value": false
          }
        },
        "widgetId": "engineCd"
      },
      {
        "action": "setprop",
        "function": "setHidden",
        "id": "dacc8d59-0da8-43df-9301-e9e87431f2a8",
        "params": {
          "hidden": {
            "datatype": "boolean",
            "scope": "fixed",
            "value": false
          }
        },
        "widgetId": "RiskEngineProjectSelector"
      },
      {
        "action": "setprop",
        "function": "setActiveLayoutName",
        "id": "0de6822c-1290-460c-9f68-a28cdd6e670d",
        "params": {
          "activeTab": {
            "datatype": "text",
            "name": "engineCd",
            "objectType": "Model",
            "scope": "field",
            "set-field": "engineCd",
            "target": "$self$"
          }
        },
        "widgetId": "CodeContainer"
      },
      {
        "action": "ifelse",
        "end": true,
        "id": "6d5dedb0-d127-42b8-8d7e-5c1ca011f587",
        "includeElse": true,
        "main": "f12a4ee6-8dc5-401a-be44-45eff52a334a",
        "test": {
          "datatype": "boolean",
          "name": "isExecTypeBEPOVERLAY",
          "scope": "local"
        }
      },
      {
        "action": "ifelse",
        "end": true,
        "id": "f5f38ac7-8a68-486e-9bf7-f26e8591e9f9",
        "includeElse": true,
        "main": "1ee96fab-b47f-4c2e-8941-c9006996ab20",
        "test": {
          "datatype": "boolean",
          "name": "isExecTypeALL",
          "scope": "local"
        }
      }
    ],
    "sasProvided": true
  },
  "onNameChange": {
    "inputs": [
      {
        "datatype": "text",
        "name": "input_value"
      }
    ],
    "logic": [
      {
        "action": "setvar",
        "id": "579eb457-5aa0-4ed7-855d-24a4ee874b70",
        "type": "calculated",
        "value": {
          "function": "getLocalisedObjectType",
          "library": "$interactions$",
          "params": {},
          "returnType": "text"
        },
        "variable": {
          "datatype": "text",
          "name": "objectType",
          "scope": "local"
        }
      },
      {
        "action": "setvar",
        "id": "15d62a50-6387-4f29-a440-dccfa73d4283",
        "type": "calculated",
        "value": {
          "function": "concat",
          "library": "CirrusLibString",
          "params": {
            "string1": {
              "datatype": "text",
              "name": "objectType",
              "scope": "local"
            },
            "string2": {
              "datatype": "text",
              "scope": "fixed",
              "value": ": "
            }
          },
          "returnType": "text"
        },
        "variable": {
          "datatype": "text",
          "name": "name_str",
          "scope": "local"
        }
      },
      {
        "action": "setvar",
        "id": "7edb0eab-2f82-48bf-b722-283144b5cbd8",
        "type": "calculated",
        "value": {
          "function": "concat",
          "library": "CirrusLibString",
          "params": {
            "string1": {
              "datatype": "text",
              "name": "name_str",
              "scope": "local"
            },
            "string2": {
              "datatype": "text",
              "name": "input_value",
              "scope": "local"
            }
          },
          "returnType": "text"
        },
        "variable": {
          "datatype": "text",
          "name": "name_readonly",
          "scope": "data",
          "target": "$self$"
        }
      }
    ],
    "sasProvided": true
  },
  "onRiskEngineProjectChange": {
    "inputs": [
      {
        "datatype": "text",
        "name": "input_value"
      }
    ],
    "logic": [
      {
        "action": "setvar",
        "id": "5fc1f907-eb3a-4fab-b9e4-b062287d3180",
        "type": "variable",
        "value": {
          "datatype": "text",
          "name": "input_value",
          "scope": "local"
        },
        "variable": {
          "datatype": "text",
          "name": "engineModelUri",
          "objectType": "Model",
          "scope": "field",
          "set-field": "engineModelUri",
          "target": "$self$"
        }
      }
    ],
    "sasProvided": true
  },
  "onSave": {
    "inputs": [],
    "logic": [
      {
        "action": "execfunc",
        "function": "clearPopups",
        "id": "f3992856-cf2f-45f7-bc32-4342e07abc87",
        "library": "CirrusLibPage",
        "params": {}
      },
      {
        "action": "setvar",
        "id": "83f46262-a47e-4c0f-be0a-cf5e0390cac4",
        "type": "calculated",
        "value": {
          "function": "getAllData",
          "library": "CirrusLibPageData",
          "params": {},
          "returnType": "All Data"
        },
        "variable": {
          "datatype": "All Data",
          "name": "data",
          "scope": "local"
        }
      },
      {
        "action": "setvar",
        "id": "c7b49def-1420-4c4d-87d1-df7c9a1c296b",
        "type": "fixed",
        "value": {
          "datatype": "text",
          "dataval": "Model"
        },
        "variable": {
          "datatype": "text",
          "name": "objectType",
          "scope": "local"
        }
      },
      {
        "action": "setvar",
        "id": "6509dc8b-375e-4dd8-8df2-58a0690d00b7",
        "type": "calculated",
        "value": {
          "function": "isDraftObject",
          "library": "CirrusLibCirrusObject",
          "params": {},
          "returnType": "boolean"
        },
        "variable": {
          "datatype": "boolean",
          "name": "isDraft",
          "scope": "local"
        }
      },
      {
        "action": "ifelse",
        "id": "8ef5922e-7c26-4913-977e-a1367c753810",
        "includeElse": true,
        "test": {
          "datatype": "boolean",
          "name": "isDraft",
          "scope": "local"
        }
      },
      {
        "action": "ifelse",
        "id": "7b76caa3-7155-45c7-ad6c-947b3c152efd",
        "includeElse": true,
        "iselse": true,
        "main": "8ef5922e-7c26-4913-977e-a1367c753810",
        "test": {
          "datatype": "boolean",
          "name": "isDraft",
          "scope": "local"
        }
      },
      {
        "action": "setvar",
        "id": "2883cd2e-2c2c-427a-81c0-2b8934445852",
        "type": "calculated",
        "value": {
          "function": "getCurrentObjectKey",
          "library": "CirrusLibPageData",
          "params": {},
          "returnType": "text"
        },
        "variable": {
          "datatype": "text",
          "name": "instanceKey",
          "scope": "local"
        }
      },
      {
        "action": "setvar",
        "id": "be333a15-7df9-49ea-86c5-227dfa37ea72",
        "type": "calculated",
        "value": {
          "function": "isObjectDeleted",
          "library": "CirrusLibCirrusObject",
          "params": {
            "objectKey": {
              "datatype": "text",
              "name": "instanceKey",
              "scope": "local"
            }
          },
          "returnType": "boolean"
        },
        "variable": {
          "datatype": "boolean",
          "name": "isObjectDeleted",
          "scope": "local"
        }
      },
      {
        "action": "ifelse",
        "id": "1e6e0ab4-9f57-482e-9f5a-4af91002ff70",
        "test": {
          "datatype": "boolean",
          "name": "isObjectDeleted",
          "scope": "local"
        }
      },
      {
        "action": "returnvar",
        "id": "e17e6614-b603-4bd7-ad43-98cc58a40e2b",
        "variable": {
          "datatype": "boolean",
          "name": "isObjectDeleted",
          "scope": "local"
        }
      },
      {
        "action": "ifelse",
        "end": true,
        "id": "0eec178e-c1e3-4611-ba79-c3f9878b5f9c",
        "main": "1e6e0ab4-9f57-482e-9f5a-4af91002ff70",
        "test": {
          "datatype": "boolean",
          "name": "isObjectDeleted",
          "scope": "local"
        }
      },
      {
        "action": "ifelse",
        "end": true,
        "id": "6a129a35-c4e9-4658-9569-ba97e1eeab1c",
        "includeElse": true,
        "main": "8ef5922e-7c26-4913-977e-a1367c753810",
        "test": {
          "datatype": "boolean",
          "name": "isDraft",
          "scope": "local"
        }
      },
      {
        "action": "execfunc",
        "function": "showLoadingOverlay",
        "id": "4f80053d-6180-43a1-a98f-6245fb1ff268",
        "library": "CirrusLibPage",
        "params": {}
      },
      {
        "action": "setvar",
        "id": "11a9cf10-a229-4bd4-b6b5-b6d7679a3da8",
        "type": "calculated",
        "value": {
          "function": "validateFields",
          "library": "CirrusLibPageData",
          "params": {},
          "returnType": "boolean"
        },
        "variable": {
          "datatype": "boolean",
          "name": "areRequiredFieldsEmpty",
          "scope": "local"
        }
      },
      {
        "action": "ifelse",
        "id": "7ae7e047-4dbb-4101-90ca-995898a53b57",
        "includeElse": true,
        "test": {
          "datatype": "boolean",
          "name": "areRequiredFieldsEmpty",
          "scope": "local"
        }
      },
      {
        "action": "ifelse",
        "id": "b440592f-5863-406d-8859-708d8601f65b",
        "includeElse": true,
        "iselse": true,
        "main": "7ae7e047-4dbb-4101-90ca-995898a53b57",
        "test": {
          "datatype": "boolean",
          "name": "areRequiredFieldsEmpty",
          "scope": "local"
        }
      },
      {
        "action": "ifelse",
        "id": "721dbf0c-9131-4c1f-bce0-b66077d6b061",
        "includeElse": true,
        "test": {
          "datatype": "boolean",
          "name": "isDraft",
          "scope": "local"
        }
      },
      {
        "action": "setvar",
        "id": "982bb5a1-4159-40d1-a42d-18ea40afb715",
        "type": "calculated",
        "value": {
          "function": "saveDraft",
          "library": "CirrusLibCirrusObject",
          "params": {
            "data": {
              "datatype": "All Data",
              "name": "data",
              "scope": "local"
            }
          },
          "returnType": "text"
        },
        "variable": {
          "datatype": "text",
          "name": "newKey",
          "scope": "local"
        }
      },
      {
        "action": "setvar",
        "id": "d79dbb3a-ff8d-4ddf-b7ca-99c4e021447a",
        "type": "calculated",
        "value": {
          "function": "toString",
          "library": "CirrusLibString",
          "params": {
            "value": {
              "datatype": "text",
              "name": "newKey",
              "scope": "local"
            }
          },
          "returnType": "text"
        },
        "variable": {
          "datatype": "text",
          "name": "newKeyString",
          "scope": "local"
        }
      },
      {
        "action": "setvar",
        "id": "62160e9c-97d0-4b52-9db1-cfcbfd4deace",
        "type": "fixed",
        "value": {
          "datatype": "text",
          "dataval": "false"
        },
        "variable": {
          "datatype": "text",
          "name": "falseString",
          "scope": "local"
        }
      },
      {
        "action": "setvar",
        "id": "852507cb-0ad2-4cac-8ea2-4b9d2a732a1b",
        "type": "calculated",
        "value": {
          "function": "strEquals",
          "library": "CirrusLibString",
          "params": {
            "string1": {
              "datatype": "text",
              "name": "newKeyString",
              "scope": "local"
            },
            "string2": {
              "datatype": "text",
              "name": "falseString",
              "scope": "local"
            }
          },
          "returnType": "boolean"
        },
        "variable": {
          "datatype": "boolean",
          "name": "isKeyFalse",
          "scope": "local"
        }
      },
      {
        "action": "ifelse",
        "id": "9b839f20-5873-4de8-aaee-c14d40381cc7",
        "includeElse": true,
        "test": {
          "datatype": "boolean",
          "name": "isKeyFalse",
          "scope": "local"
        }
      },
      {
        "action": "ifelse",
        "id": "7c972b57-006f-4f47-b742-d2c0891afd31",
        "includeElse": true,
        "iselse": true,
        "main": "9b839f20-5873-4de8-aaee-c14d40381cc7",
        "test": {
          "datatype": "boolean",
          "name": "isKeyFalse",
          "scope": "local"
        }
      },
      {
        "action": "setvar",
        "id": "8a9e309b-3da2-47d0-abfa-94873690aa8a",
        "type": "calculated",
        "value": {
          "function": "getEditLocation",
          "library": "CirrusLibNav",
          "params": {
            "key": {
              "datatype": "text",
              "name": "newKey",
              "scope": "local"
            },
            "objectType": {
              "datatype": "text",
              "name": "objectType",
              "scope": "local"
            }
          },
          "returnType": "text"
        },
        "variable": {
          "datatype": "text",
          "name": "newLocation",
          "scope": "local"
        }
      },
      {
        "action": "setvar",
        "id": "43411c54-db06-4403-a902-82d933ef3aad",
        "type": "fixed",
        "value": {
          "datatype": "boolean",
          "dataval": true
        },
        "variable": {
          "datatype": "boolean",
          "name": "replaceInBrowser",
          "scope": "local"
        }
      },
      {
        "action": "execfunc",
        "function": "navigate",
        "id": "f808b680-a3f3-4f46-b3ad-f8865e47be6f",
        "library": "CirrusLibNav",
        "params": {
          "location": {
            "datatype": "text",
            "name": "newLocation",
            "scope": "local"
          },
          "replace": {
            "datatype": "boolean",
            "name": "replaceInBrowser",
            "scope": "local"
          }
        },
        "returnType": "text"
      },
      {
        "action": "execfunc",
        "function": "showSuccess",
        "id": "6eb5e624-ab65-46ed-80db-56831082c67b",
        "library": "CirrusLibPage",
        "params": {}
      },
      {
        "action": "ifelse",
        "end": true,
        "id": "2bac73bd-7f7a-405f-af0c-6c6940725af0",
        "includeElse": true,
        "main": "9b839f20-5873-4de8-aaee-c14d40381cc7",
        "test": {
          "datatype": "boolean",
          "name": "isKeyFalse",
          "scope": "local"
        }
      },
      {
        "action": "ifelse",
        "id": "f1b1d7da-65b1-4336-8254-05b59f526e6d",
        "includeElse": true,
        "iselse": true,
        "main": "721dbf0c-9131-4c1f-bce0-b66077d6b061",
        "test": {
          "datatype": "boolean",
          "name": "isDraft",
          "scope": "local"
        }
      },
      {
        "action": "setvar",
        "id": "6ece9d2f-9cdd-4f8e-bafb-09f1dd277391",
        "type": "calculated",
        "value": {
          "function": "getCurrentObjectKey",
          "library": "CirrusLibPageData",
          "params": {},
          "returnType": "text"
        },
        "variable": {
          "datatype": "text",
          "name": "instanceKey",
          "scope": "local"
        }
      },
      {
        "action": "setvar",
        "id": "a56483d7-cee4-4537-997d-6c1c21ff5f2e",
        "type": "calculated",
        "value": {
          "function": "saveObject",
          "library": "CirrusLibCirrusObject",
          "params": {
            "data": {
              "datatype": "All Data",
              "name": "data",
              "scope": "local"
            }
          },
          "returnType": "boolean"
        },
        "variable": {
          "datatype": "boolean",
          "name": "saveSuccessful",
          "scope": "local"
        }
      },
      {
        "action": "ifelse",
        "id": "9decbe4f-2612-4fb0-84a6-9809e8703931",
        "test": {
          "datatype": "boolean",
          "name": "saveSuccessful",
          "scope": "local"
        }
      },
      {
        "action": "execfunc",
        "function": "onEditLoad",
        "id": "0c0adb92-4cba-4579-97e5-04f78e95abec",
        "library": "$interactions$",
        "params": {
          "input_key": {
            "datatype": "text",
            "name": "instanceKey",
            "scope": "local"
          }
        }
      },
      {
        "action": "execfunc",
        "function": "showSuccess",
        "id": "697964c6-e97e-40a4-848b-f1b8f71954f0",
        "library": "CirrusLibPage",
        "params": {}
      },
      {
        "action": "ifelse",
        "end": true,
        "id": "cd642d84-fe45-4051-aeb1-0fb02e6686f7",
        "main": "9decbe4f-2612-4fb0-84a6-9809e8703931",
        "test": {
          "datatype": "boolean",
          "name": "saveSuccessful",
          "scope": "local"
        }
      },
      {
        "action": "ifelse",
        "end": true,
        "id": "86e31acc-082f-45a5-9aff-c68a17b5c5ec",
        "includeElse": true,
        "main": "721dbf0c-9131-4c1f-bce0-b66077d6b061",
        "test": {
          "datatype": "boolean",
          "name": "isDraft",
          "scope": "local"
        }
      },
      {
        "action": "ifelse",
        "end": true,
        "id": "0bae1c46-9167-47b7-ae6f-d533d5c5167a",
        "includeElse": true,
        "main": "7ae7e047-4dbb-4101-90ca-995898a53b57",
        "test": {
          "datatype": "boolean",
          "name": "areRequiredFieldsEmpty",
          "scope": "local"
        }
      },
      {
        "action": "execfunc",
        "function": "hideLoadingOverlay",
        "id": "f741174e-bee0-40a6-8671-a67e785dd732",
        "library": "CirrusLibPage",
        "params": {}
      }
    ],
    "sasProvided": true
  },
  "onTabClose": {
    "inputs": [],
    "logic": [
      {
        "action": "setvar",
        "id": "d4bc8813-7b01-4a4a-aa39-9179a9f3f8b6",
        "type": "calculated",
        "value": {
          "function": "getDiffJSONPatch",
          "library": "CirrusLibPageData",
          "params": {},
          "returnType": "Patch array"
        },
        "variable": {
          "datatype": "Patch array",
          "name": "patch",
          "scope": "local"
        }
      },
      {
        "action": "setvar",
        "id": "7137fef9-ed0f-4eeb-bb91-312044fd126e",
        "type": "calculated",
        "value": {
          "function": "isObjectPageDirty",
          "library": "CirrusLibCirrusObject",
          "params": {
            "patch": {
              "datatype": "Patch array",
              "name": "patch",
              "scope": "local"
            }
          },
          "returnType": "boolean"
        },
        "variable": {
          "datatype": "boolean",
          "name": "isDirty",
          "scope": "local"
        }
      },
      {
        "action": "ifelse",
        "id": "b4baa254-da5a-4791-85dd-4cf604d92946",
        "includeElse": false,
        "test": {
          "datatype": "boolean",
          "name": "isDirty",
          "scope": "local"
        }
      },
      {
        "action": "setvar",
        "id": "4cb612e0-2294-4e78-b25f-7afea93e4d5d",
        "type": "calculated",
        "value": {
          "function": "promptForConfirmNavigation",
          "library": "CirrusLibPage",
          "params": {},
          "returnType": "boolean"
        },
        "variable": {
          "datatype": "boolean",
          "name": "closeAnyway",
          "scope": "local"
        }
      },
      {
        "action": "returnvar",
        "id": "d40aa399-590e-4b19-b8c5-0ea908c08bdf",
        "variable": {
          "datatype": "boolean",
          "name": "closeAnyway",
          "scope": "local"
        }
      },
      {
        "action": "ifelse",
        "end": true,
        "id": "817bd86e-4653-4dbf-9408-3471d42e4f6e",
        "includeElse": false,
        "main": "b4baa254-da5a-4791-85dd-4cf604d92946",
        "test": {
          "datatype": "boolean",
          "name": "isDirty",
          "scope": "local"
        }
      },
      {
        "action": "setvar",
        "id": "bc1b02e8-8f69-4079-b6f4-ec2b58cbf408",
        "type": "calculated",
        "value": {
          "function": "not",
          "library": "CirrusLibBoolean",
          "params": {
            "bool": {
              "datatype": "boolean",
              "name": "isDirty",
              "scope": "local"
            }
          },
          "returnType": "boolean"
        },
        "variable": {
          "datatype": "boolean",
          "name": "canClose",
          "scope": "local"
        }
      },
      {
        "action": "returnvar",
        "id": "91f8c96d-6a83-4f16-9083-517045695ad4",
        "variable": {
          "datatype": "boolean",
          "name": "canClose",
          "scope": "local"
        }
      }
    ],
    "sasProvided": true
  },
  "setDefaultName": {
    "inputs": [
      {
        "datatype": "text",
        "name": "input_value"
      }
    ],
    "logic": [
      {
        "action": "setvar",
        "id": "15865878-e008-482d-9536-e55d0392b90b",
        "isCommented": false,
        "type": "calculated",
        "value": {
          "function": "toBoolean",
          "library": "CirrusLibBoolean",
          "params": {
            "value": {
              "datatype": "text",
              "name": "name",
              "objectType": "Model",
              "scope": "field",
              "set-field": "name",
              "target": "$self$"
            }
          },
          "returnType": "boolean"
        },
        "variable": {
          "datatype": "boolean",
          "name": "isNameSet",
          "scope": "local"
        }
      },
      {
        "action": "setvar",
        "id": "7b2485a3-f768-4676-955a-ba03c89f0823",
        "isCommented": false,
        "type": "calculated",
        "value": {
          "datatype": "boolean",
          "function": "not",
          "library": "CirrusLibBoolean",
          "params": {
            "bool": {
              "datatype": "boolean",
              "name": "isNameSet",
              "scope": "local"
            }
          },
          "returnType": "boolean"
        },
        "variable": {
          "datatype": "boolean",
          "name": "isNameSet",
          "scope": "local"
        }
      },
      {
        "action": "ifelse",
        "id": "33bd709a-ab05-4f49-b9f2-ee302761e19e",
        "isCommented": false,
        "test": {
          "datatype": "boolean",
          "name": "isNameSet",
          "scope": "local"
        }
      },
      {
        "action": "setvar",
        "id": "84b55b4a-a6f1-43cb-a298-604c759629bd",
        "isCommented": false,
        "type": "calculated",
        "value": {
          "function": "getLocalisedObjectType",
          "library": "$interactions$",
          "params": {},
          "returnType": "text"
        },
        "variable": {
          "datatype": "text",
          "name": "objectType",
          "scope": "local"
        }
      },
      {
        "action": "setvar",
        "id": "2b608e58-0a00-4e13-bc33-59626adef149",
        "isCommented": false,
        "type": "calculated",
        "value": {
          "function": "concat",
          "library": "CirrusLibString",
          "params": {
            "string1": {
              "datatype": "text",
              "name": "objectType",
              "scope": "local"
            },
            "string2": {
              "datatype": "text",
              "scope": "fixed",
              "value": ": "
            }
          },
          "returnType": "text"
        },
        "variable": {
          "datatype": "text",
          "name": "name_str",
          "scope": "local"
        }
      },
      {
        "action": "setvar",
        "id": "2aacbf19-c1b4-4c4e-9412-e0b38acce35f",
        "isCommented": false,
        "type": "calculated",
        "value": {
          "function": "concat",
          "library": "CirrusLibString",
          "params": {
            "string1": {
              "datatype": "text",
              "name": "name_str",
              "scope": "local"
            },
            "string2": {
              "datatype": "text",
              "name": "input_value",
              "scope": "local"
            }
          },
          "returnType": "text"
        },
        "variable": {
          "datatype": "text",
          "name": "name_readonly",
          "scope": "data",
          "target": "$self$"
        }
      },
      {
        "action": "setvar",
        "id": "80f4def2-409b-4076-8a54-796f151085e2",
        "isCommented": false,
        "type": "variable",
        "value": {
          "datatype": "text",
          "name": "input_value",
          "scope": "local"
        },
        "variable": {
          "datatype": "text",
          "name": "name",
          "objectType": "Model",
          "scope": "field",
          "set-field": "name",
          "target": "$self$"
        }
      },
      {
        "action": "ifelse",
        "end": true,
        "id": "17510bd4-7228-4f3e-aeb3-94a8e3ee8a10",
        "isCommented": false,
        "main": "33bd709a-ab05-4f49-b9f2-ee302761e19e",
        "test": {
          "datatype": "boolean",
          "name": "isNameSet",
          "scope": "local"
        }
      }
    ],
    "sasProvided": true
  },
  "setEngineDropdown": {
    "inputs": [
      {
        "datatype": "boolean",
        "name": "input_isREAvailable"
      }
    ],
    "logic": [
      {
        "action": "setvar",
        "id": "722666d1-7323-470a-bd8d-b2e1840f7651",
        "isCommented": false,
        "type": "variable",
        "value": {
          "datatype": "boolean",
          "name": "input_isREAvailable",
          "scope": "local"
        },
        "variable": {
          "datatype": "boolean",
          "name": "isREAvailable",
          "scope": "local"
        }
      },
      {
        "action": "addComment",
        "commentStep": "Get the list of options from the NamedList model_engines. if Risk Engine is not available, remove that option from the list.",
        "id": "9ba8211a-9448-4a13-bcd2-1111aca55965",
        "isCommented": false
      },
      {
        "action": "setvar",
        "id": "d58ce8ff-66dc-4748-926e-7da89b90b7dd",
        "isCommented": false,
        "type": "calculated",
        "value": {
          "function": "getNamedListOptionsAsValueLabelPair",
          "library": "CirrusLibCirrusObjectNamedList",
          "params": {
            "listName": {
              "datatype": "text",
              "scope": "fixed",
              "value": "model_engines"
            }
          },
          "returnType": "\u003cOutgoing\u003e array"
        },
        "variable": {
          "datatype": "\u003cOutgoing\u003e array",
          "name": "options",
          "scope": "local"
        }
      },
      {
        "action": "ifelse",
        "id": "9781540f-e908-4ca8-b715-cd09e66d6781",
        "includeElse": true,
        "isCommented": false,
        "test": {
          "datatype": "boolean",
          "name": "isREAvailable",
          "scope": "local"
        }
      },
      {
        "action": "ifelse",
        "id": "4a27af56-6168-491d-95a5-eb90d392a1bb",
        "includeElse": true,
        "isCommented": false,
        "iselse": true,
        "main": "9781540f-e908-4ca8-b715-cd09e66d6781",
        "test": {
          "datatype": "boolean",
          "name": "isREAvailable",
          "scope": "local"
        }
      },
      {
        "action": "setvar",
        "id": "7d786f53-4969-45bb-a3bc-87dd1308c491",
        "isCommented": false,
        "type": "calculated",
        "value": {
          "function": "filterObjects",
          "library": "CirrusLibArray",
          "params": {
            "array": {
              "datatype": "\u003cIncoming\u003e array array",
              "name": "options",
              "scope": "local"
            },
            "operator": {
              "datatype": "enum",
              "scope": "fixed",
              "value": "neq"
            },
            "propertyName": {
              "datatype": "text",
              "scope": "fixed",
              "value": "value"
            },
            "referenceValue": {
              "datatype": "\u003cIncoming\u003e array",
              "scope": "fixed",
              "value": "RE"
            }
          },
          "returnType": "\u003cIncoming\u003e array array array array array array array array array array array array"
        },
        "variable": {
          "datatype": "\u003cIncoming\u003e array array array array array array array array array array array array",
          "name": "options",
          "scope": "local"
        }
      },
      {
        "action": "ifelse",
        "end": true,
        "id": "66a567d0-cee2-425e-851b-33e73299a1fb",
        "includeElse": true,
        "isCommented": false,
        "main": "9781540f-e908-4ca8-b715-cd09e66d6781",
        "test": {
          "datatype": "boolean",
          "name": "isREAvailable",
          "scope": "local"
        }
      },
      {
        "action": "setprop",
        "function": "filterValues",
        "id": "d692d8a1-254b-4b52-965b-8333855a02ff",
        "isCommented": false,
        "params": {
          "filteredValues": {
            "datatype": "\u003cIncoming\u003e array array array array array array array array array array array array",
            "name": "options",
            "scope": "local"
          }
        },
        "scope": "currentPage",
        "widgetId": "engineCd"
      }
    ],
    "resolveEachStep": false,
    "sasProvided": true
  },
  "setModelExecTypeDefault": {
    "inputs": [],
    "logic": [
      {
        "action": "setvar",
        "id": "c99fb95c-3668-4cda-808f-8353f365aaf5",
        "isCommented": false,
        "type": "fixed",
        "value": {
          "datatype": "text",
          "dataval": "ANA"
        },
        "variable": {
          "datatype": "text",
          "name": "execTypeCd",
          "objectType": "Model",
          "scope": "field",
          "set-field": "execTypeCd",
          "target": "$self$"
        }
      }
    ],
    "resolveEachStep": false,
    "sasProvided": true
  },
  "setReadOnlyFields": {
    "inputs": [],
    "logic": [
      {
        "action": "setvar",
        "id": "cdc41e04-d94f-46a7-9c18-6b9c248c1be5",
        "type": "calculated",
        "value": {
          "function": "isDraftObject",
          "library": "CirrusLibCirrusObject",
          "params": {},
          "returnType": "boolean"
        },
        "variable": {
          "datatype": "boolean",
          "name": "isDraft",
          "scope": "local"
        }
      },
      {
        "action": "setvar",
        "id": "bf5936c8-6b1b-4aea-aa48-50ff6993cd19",
        "type": "calculated",
        "value": {
          "function": "getObjectCapabilities",
          "library": "CirrusLibCirrusObject",
          "params": {
            "objectType": {
              "datatype": "text",
              "scope": "fixed",
              "value": "Model"
            }
          },
          "returnType": "text array"
        },
        "variable": {
          "datatype": "text array",
          "name": "userCapabilities",
          "scope": "local"
        }
      },
      {
        "action": "setvar",
        "id": "c75fd888-fea3-4c53-84e4-4b09d1a267dc",
        "type": "calculated",
        "value": {
          "function": "contains",
          "library": "CirrusLibArray",
          "params": {
            "array": {
              "datatype": "text array",
              "name": "userCapabilities",
              "scope": "local"
            },
            "value": {
              "datatype": "text",
              "scope": "fixed",
              "value": "create"
            }
          },
          "returnType": "boolean"
        },
        "variable": {
          "datatype": "boolean",
          "name": "userCanCreate",
          "scope": "local"
        }
      },
      {
        "action": "setvar",
        "id": "f62649e4-1f3b-4926-93eb-10731dda0f3c",
        "type": "calculated",
        "value": {
          "function": "not",
          "library": "CirrusLibBoolean",
          "params": {
            "bool": {
              "datatype": "boolean",
              "name": "userCanCreate",
              "scope": "local"
            }
          },
          "returnType": "boolean"
        },
        "variable": {
          "datatype": "boolean",
          "name": "userCannotCreate",
          "scope": "local"
        }
      },
      {
        "action": "setvar",
        "id": "f0c03d38-f711-47c7-b282-deb6b9321fd7",
        "type": "calculated",
        "value": {
          "function": "contains",
          "library": "CirrusLibArray",
          "params": {
            "array": {
              "datatype": "text array",
              "name": "userCapabilities",
              "scope": "local"
            },
            "value": {
              "datatype": "text",
              "scope": "fixed",
              "value": "update"
            }
          },
          "returnType": "boolean"
        },
        "variable": {
          "datatype": "boolean",
          "name": "userCanUpdate",
          "scope": "local"
        }
      },
      {
        "action": "setvar",
        "id": "86f2e39d-011f-4daf-aeda-f2aa5f35d35b",
        "type": "calculated",
        "value": {
          "function": "not",
          "library": "CirrusLibBoolean",
          "params": {
            "bool": {
              "datatype": "boolean",
              "name": "userCanUpdate",
              "scope": "local"
            }
          },
          "returnType": "boolean"
        },
        "variable": {
          "datatype": "boolean",
          "name": "userCannotUpdate",
          "scope": "local"
        }
      },
      {
        "action": "setvar",
        "id": "6c4353f3-e94b-4e1a-81be-a2ed8a6c3fec",
        "type": "calculated",
        "value": {
          "datatype": "boolean",
          "function": "isDraftObject",
          "library": "CirrusLibCirrusObject",
          "params": {},
          "returnType": "boolean"
        },
        "variable": {
          "datatype": "boolean",
          "name": "isDraft",
          "scope": "local"
        }
      },
      {
        "action": "ifelse",
        "id": "8f963f33-cf24-4cc1-9f62-db9c6dc0ebca",
        "includeElse": true,
        "test": {
          "datatype": "boolean",
          "name": "isDraft",
          "scope": "local"
        }
      },
      {
        "action": "setprop",
        "function": "setReadOnly",
        "id": "145dcd3e-e251-4427-929c-5b09fb8bac2b",
        "params": {
          "readOnly": {
            "datatype": "boolean",
            "name": "userCannotCreate",
            "scope": "local"
          }
        },
        "scope": "currentPage",
        "widgetId": "model_details"
      },
      {
        "action": "setprop",
        "function": "setReadOnly",
        "id": "97856595-03ee-4b22-ad46-1e4ca238b298",
        "params": {
          "readOnly": {
            "datatype": "boolean",
            "name": "userCannotCreate",
            "scope": "local"
          }
        },
        "scope": "currentPage",
        "widgetId": "modelPostCode"
      },
      {
        "action": "setprop",
        "function": "setReadOnly",
        "id": "b43aee41-4b15-4561-8ae8-6dada4148ae2",
        "params": {
          "readOnly": {
            "datatype": "boolean",
            "name": "userCannotCreate",
            "scope": "local"
          }
        },
        "scope": "currentPage",
        "widgetId": "modelPreCode"
      },
      {
        "action": "setprop",
        "function": "setReadOnly",
        "id": "4136d90b-209e-486b-ac7a-cb1f259bb358",
        "params": {
          "readOnly": {
            "datatype": "boolean",
            "name": "userCannotCreate",
            "scope": "local"
          }
        },
        "widgetId": "model_tabs"
      },
      {
        "action": "ifelse",
        "id": "836c95be-6b14-4413-8dcd-d23292563821",
        "includeElse": true,
        "iselse": true,
        "main": "8f963f33-cf24-4cc1-9f62-db9c6dc0ebca",
        "test": {
          "datatype": "boolean",
          "name": "isDraft",
          "scope": "local"
        }
      },
      {
        "action": "ifelse",
        "id": "bbcd4bd4-9047-452b-a61b-a593388d7152",
        "test": {
          "datatype": "boolean",
          "name": "userCannotUpdate",
          "scope": "local"
        }
      },
      {
        "action": "setprop",
        "function": "setReadOnly",
        "id": "e715afc2-61b5-4bb2-8130-6bfd9ae78281",
        "params": {
          "readOnly": {
            "datatype": "boolean",
            "name": "userCannotUpdate",
            "scope": "local"
          }
        },
        "scope": "currentPage",
        "widgetId": "statusCd"
      },
      {
        "action": "setprop",
        "function": "setReadOnly",
        "id": "3d2407b1-8312-4e9e-8b4b-9427ac476c2b",
        "params": {
          "readOnly": {
            "datatype": "boolean",
            "name": "userCannotUpdate",
            "scope": "local"
          }
        },
        "widgetId": "model_tabs"
      },
      {
        "action": "setprop",
        "function": "setReadOnly",
        "id": "c8aada07-8896-4ccf-bf59-437f9a1d0679",
        "params": {
          "readOnly": {
            "datatype": "boolean",
            "name": "userCannotUpdate",
            "scope": "local"
          }
        },
        "scope": "currentPage",
        "widgetId": "modelPreCode"
      },
      {
        "action": "setprop",
        "function": "setReadOnly",
        "id": "ec913c8d-2a9d-44c1-b8cc-ecafbe92b981",
        "params": {
          "readOnly": {
            "datatype": "boolean",
            "name": "userCannotUpdate",
            "scope": "local"
          }
        },
        "scope": "currentPage",
        "widgetId": "modelPostCode"
      },
      {
        "action": "ifelse",
        "end": true,
        "id": "d0b14bba-2220-4521-a369-2bd7ed686fa0",
        "main": "bbcd4bd4-9047-452b-a61b-a593388d7152",
        "test": {
          "datatype": "boolean",
          "name": "userCannotUpdate",
          "scope": "local"
        }
      },
      {
        "action": "ifelse",
        "end": true,
        "id": "b00ec5f9-0d2a-47bd-b55c-45a39c5e7426",
        "includeElse": true,
        "main": "8f963f33-cf24-4cc1-9f62-db9c6dc0ebca",
        "test": {
          "datatype": "boolean",
          "name": "isDraft",
          "scope": "local"
        }
      }
    ],
    "resolveEachStep": false,
    "sasProvided": true
  },
  "setRequiredFields": {
    "inputs": [],
    "logic": [
      {
        "action": "setvar",
        "id": "9e8a020d-793b-4189-830c-197eb0327c9a",
        "type": "fixed",
        "value": {
          "datatype": "boolean",
          "dataval": true
        },
        "variable": {
          "datatype": "boolean",
          "name": "isRequiredAlways",
          "scope": "local"
        }
      },
      {
        "action": "setprop",
        "function": "setRequired",
        "id": "01ae1484-0293-4ee0-85b5-210c8940eead",
        "params": {
          "required": {
            "datatype": "boolean",
            "name": "isRequiredAlways",
            "scope": "local"
          }
        },
        "scope": "currentPage",
        "widgetId": "objectId"
      },
      {
        "action": "setprop",
        "function": "setRequired",
        "id": "9445aeab-558c-43b7-85a5-734cb5d39fad",
        "params": {
          "required": {
            "datatype": "boolean",
            "name": "isRequiredAlways",
            "scope": "local"
          }
        },
        "scope": "currentPage",
        "widgetId": "name"
      },
      {
        "action": "setprop",
        "function": "setRequired",
        "id": "f4608232-876b-43f3-9050-81decf211842",
        "params": {
          "required": {
            "datatype": "boolean",
            "name": "isRequiredAlways",
            "scope": "local"
          }
        },
        "scope": "currentPage",
        "widgetId": "engineCd"
      },
      {
        "action": "setprop",
        "function": "setRequired",
        "id": "9d0e02ac-e515-4322-a82f-7aefed35d3b6",
        "params": {
          "required": {
            "datatype": "boolean",
            "name": "isRequiredAlways",
            "scope": "local"
          }
        },
        "scope": "currentPage",
        "widgetId": "statusCd"
      },
      {
        "action": "execfunc",
        "function": "disableRelatedObjectTab",
        "id": "e8891be8-c9a4-4ce5-adb7-f0b1ba58460a",
        "isCommented": false,
        "library": "$interactions$",
        "params": {}
      }
    ],
    "sasProvided": true
  }
}
